{
    "uuid": [
        {
            "value": "e779c430-6e92-4b73-ba05-140520f8efa8"
        }
    ],
    "langcode": [
        {
            "value": "en"
        }
    ],
    "type": [
        {
            "target_id": "hero",
            "target_type": "paragraphs_type",
            "target_uuid": "1678f17b-44eb-4043-9a6f-296bf6294737"
        }
    ],
    "status": [
        {
            "value": true
        }
    ],
    "created": [
        {
            "value": "2019-01-13T18:11:54+00:00",
            "format": "Y-m-d\\TH:i:sP"
        }
    ],
    "behavior_settings": [
        {
            "value": []
        }
    ],
    "default_langcode": [
        {
            "value": true
        }
    ],
    "revision_translation_affected": [
        {
            "value": true
        }
    ],
    "field_alignment": [
        {
            "value": "right"
        }
    ],
    "field_class": [],
    "field_file": [
        {
            "display": true,
            "description": "",
            "target_type": "file",
            "target_uuid": "916d5c3b-c403-4ba9-9a0e-c3a8eefe0ddf"
        }
    ],
    "field_headline": [
        {
            "value": "Commit your content"
        }
    ],
    "field_link": [],
    "field_text": [
        {
            "value": "<p>With Tome, your content is stored as static JSON files. Make a change, commit it, and spin down Drupal.<\/p>\r\n",
            "format": "rich_text"
        }
    ]
}